{
  "tests": [
    {
      "name": "test_read_file",
      "setup": "pip install -r requirements.txt",
      "run": "pytest test_assignment.py::test_read_file",
      "timeout": 5,
      "points": 2
    },
    {
      "name": "test_write_file",
      "setup": "pip install -r requirements.txt",
      "run": "pytest test_assignment.py::test_write_file",
      "timeout": 5,
      "points": 2
    },
    {
      "name": "test_list_files_in_directory",
      "setup": "pip install -r requirements.txt",
      "run": "pytest test_assignment.py::test_list_files_in_directory",
      "timeout": 5,
      "points": 2
    },
    {
      "name": "test_generate_numbers",
      "setup": "pip install -r requirements.txt",
      "run": "pytest test_assignment.py::test_generate_numbers",
      "timeout": 5,
      "points": 1
    },
    {
      "name": "test_use_function_from_module",
      "setup": "pip install -r requirements.txt",
      "run": "pytest test_assignment.py::test_use_function_from_module",
      "timeout": 5,
      "points": 3
    }
  ]
}